tabmap/config.py
tabmap/evaluate_model.py
tabmap/tabmap_construction.py
tabmap/__pycache__/config.cpython-310.pyc
tabmap/__pycache__/evaluate_model.cpython-310.pyc
tabmap/__pycache__/tabmap_construction.cpython-310.pyc
tabmap/dataloader/__init__.py
tabmap/dataloader/data_loader.py
tabmap/dataloader/dataset.py
tabmap/dataloader/__pycache__/__init__.cpython-310.pyc
tabmap/dataloader/__pycache__/data_loader.cpython-310.pyc
tabmap/dataloader/__pycache__/dataset.cpython-310.pyc
tabmap/hparams_tuner/__init__.py
tabmap/hparams_tuner/dl_models_tuner.py
tabmap/hparams_tuner/ml_models_tuner.py
tabmap/hparams_tuner/__pycache__/__init__.cpython-310.pyc
tabmap/hparams_tuner/__pycache__/dl_models_tuner.cpython-310.pyc
tabmap/hparams_tuner/__pycache__/ml_models_tuner.cpython-310.pyc
tabmap/models/CNN_2d.py
tabmap/models/__init__.py
tabmap/models/soft_ordering_CNN_1d.py
tabmap/models/tabnet.py
tabmap/models/tabtransformer.py
tabmap/models/__pycache__/CNN_2d.cpython-310.pyc
tabmap/models/__pycache__/__init__.cpython-310.pyc
tabmap/models/__pycache__/soft_ordering_CNN_1d.cpython-310.pyc
tabmap/models/__pycache__/tabnet.cpython-310.pyc
tabmap/models/__pycache__/tabtransformer.cpython-310.pyc
tabmap/utils/OT_solver.py
tabmap/utils/__init__.py
tabmap/utils/data_util.py
tabmap/utils/tabmap_visualization.py
tabmap/utils/__pycache__/OT_solver.cpython-310.pyc
tabmap/utils/__pycache__/__init__.cpython-310.pyc
tabmap/utils/__pycache__/data_util.cpython-310.pyc
tabmap-0.1.3.dist-info/LICENSE
tabmap-0.1.3.dist-info/METADATA
tabmap-0.1.3.dist-info/WHEEL
tabmap-0.1.3.dist-info/top_level.txt
tabmap-0.1.3.dist-info/RECORD
