Metadata-Version: 2.1
Name: tabmap
Version: 0.1.3
Summary: A Python package for tabular data analysis using TabMap.
Author-email: Rui Yan <ruiyan820@gmail.com>
License: Creative Commons Attribution-NonCommercial-NoDerivs 2.0
Project-URL: Homepage, https://github.com/rui-yan/TabMap
Project-URL: Source, https://github.com/rui-yan/TabMap
Project-URL: Tracker, https://github.com/rui-yan/TabMap/issues
Keywords: tabular data,data analysis,machine learning,data visualization
Classifier: Development Status :: 3 - Alpha
Classifier: Intended Audience :: Science/Research
Classifier: Intended Audience :: Developers
Classifier: Topic :: Software Development :: Build Tools
Classifier: Topic :: Scientific/Engineering :: Information Analysis
Classifier: License :: OSI Approved :: MIT License
Classifier: Programming Language :: Python :: 3
Classifier: Programming Language :: Python :: 3.8
Classifier: Programming Language :: Python :: 3.9
Classifier: Programming Language :: Python :: 3.10
Classifier: Operating System :: OS Independent
License-File: LICENSE
Requires-Dist: numpy>=1.23.1
Requires-Dist: scikit-learn>=1.4.2
Requires-Dist: torch>=1.13.1
Requires-Dist: torchvision>=0.14.1
Requires-Dist: pot>=0.9.2
Requires-Dist: optuna>=3.3.0
Requires-Dist: seaborn>=0.12.2
Requires-Dist: gower==0.1.2
Requires-Dist: pandas>=1.5.3
Requires-Dist: pytorch-tabnet
Requires-Dist: tab-transformer-pytorch
Requires-Dist: xgboost
